{
  "hash": "3fbeeb2fec8de75b982037f6fc382470",
  "result": {
    "engine": "jupyter",
    "markdown": "---\ntitle: \"Palmer Penguin Analysis\"\nformat: html\njupyter: python3\n---\n\n\n## 1. 분석 개요 및 목표\n\n-   펭귄 3종(Adelie, Gentoo, Chinstrap)별 특징을 알아보자!\n\n## 2. 데이터소개\n\n-   **주요 변수:**\n    -   **신체 특성:** 부리 길이(`bill_length_mm`), 부리 깊이(`bill_depth_mm`), 날개 길이(`flip_len_mm`), 체중(`body_mass_g`)\n    -   **서식지:** 섬(`island`), 종(`species`), 성별(`sex`)\n    -   **연도:** 데이터 수집 연도(`year`)\n\n## 3. 분석 내용\n\n#### 3.1 종별 서식지\n\n|         | Adelie | Gentoo | Chinstrap |\n|:-------:|:------:|:------:|:---------:|\n| Torgers |   O    |   X    |     X     |\n| Biscoe  |   O    |   O    |     X     |\n|  Dream  |   O    |   X    |     O     |\n\n| species   | island                       |\n|-----------|------------------------------|\n| Adelie    | Torgersen', 'Biscoe', 'Dream |\n| Gentoo    | 'Biscoe                      |\n| Chinstrap | Dream                        |\n\n#### 상기 index는 다음을 나타낸다.\n\nGentoo펭귄은 Biscoe섬만 서식한다.\n\nChinstrap펭귄은 Dream섬에서만 서식한다.\n\nAdelie펭귄은 Torgers, Biscoe, Dream 전지역에서 서식한다.\n\n## 3.2 종별 신체 특성\n\n#### 3.2.1 종별 부리 길이(최소/최대/중앙값/평균)\n\n| species | ('bill_length_mm', 'min') | ('bill_length_mm', 'max') | ('bill_length_mm', 'median') | ('bill_length_mm', 'mean') |\n|:--------------|--------------:|--------------:|--------------:|--------------:|\n| Adelie | 32.1 | 46 | 38.8 | 38.7914 |\n| Chinstrap | 40.9 | 58 | 49.55 | 48.8338 |\n| Gentoo | 40.9 | 59.6 | 47.3 | 47.5049 |\n\n1.  Adelie 펭귄의 부리 길이가 가장 짧으며, 평균적으로 약 38.79mm이다.\n2.  Chinstrap 펭귄이 가장 긴 부리를 가지며, 평균적으로 48.83mm로 측정됨.\n3.  Gentoo 펭귄의 부리 길이는 Chinstrap보다는 짧지만, Adelie보다는 길다.\n\n#### 3.2.2 종별 부리 넓이(최소/최대/중앙값/평균)\n\n| species | ('bill_depth_mm', 'min') | ('bill_depth_mm', 'max') | ('bill_depth_mm', 'median') | ('bill_depth_mm', 'mean') |\n|:--------------|--------------:|--------------:|--------------:|--------------:|\n| Adelie | 15.5 | 21.5 | 18.4 | 18.3464 |\n| Chinstrap | 16.4 | 20.8 | 18.45 | 18.4206 |\n| Gentoo | 13.1 | 17.3 | 15 | 14.9821 |\n\n```         \n1. Adelie 펭귄의 부리 길이가 가장 짧으며, 평균적으로 약 38.79mm이다.\n2. Chinstrap 펭귄이 가장 긴 부리를 가지며, 평균적으로 48.83mm로 측정됨.\n3. Gentoo 펭귄의 부리 길이는 Chinstrap보다는 짧지만, Adelie보다는 길다.\n```\n\n#### 3.2.3 종별 날개 길이(최소/최대/중앙값/평균)\n\n| species | ('flip_len_mm', 'min') | ('flip_len_mm', 'max') | ('flip_len_mm', 'median') | ('flip_len_mm', 'mean') |\n|:--------------|--------------:|--------------:|--------------:|--------------:|\n| Adelie | 172 | 210 | 190 | 189.954 |\n| Chinstrap | 178 | 212 | 196 | 195.824 |\n| Gentoo | 203 | 231 | 216 | 217.187 |\n\n1.  Gentoo 펭귄이 가장 긴 날개를 가짐 (평균 217.19mm)\n2.  Adelie 펭귄의 날개 길이가 가장 짧음 (평균 189.95mm)\n3.  Chinstrap 펭귄은 Adelie와 Gentoo 사이에 위치 (평균 195.82mm)\n\n#### 3.2.4 종별 몸무게(최소/최대/중앙값/평균)\n\n| species | ('body_mass_g', 'min') | ('body_mass_g', 'max') | ('body_mass_g', 'median') | ('body_mass_g', 'mean') |\n|:--------------|--------------:|--------------:|--------------:|--------------:|\n| Adelie | 2850 | 4775 | 3700 | 3700.66 |\n| Chinstrap | 2700 | 4800 | 3700 | 3733.09 |\n| Gentoo | 3950 | 6300 | 5000 | 5076.02 |\n\n1. Gentoo 펭귄이 가장 무겁다 (평균 체중 5076.02g, 중앙값 5000g)\n2. Adelie와 Chinstrap 펭귄의 평균 체중은 비슷하지만, Chinstrap이 약간 더 무거움.\n3. **Adelie 펭귄의 최소 체중(2850g)**이 가장 가벼움, 반면 **Gentoo 펭귄의 최대 체중(6300g)**이 가장 무거움.\n\n## 3.3 평균 요약\n\n|           | bill_length_mm | bill_depth_mm | flipper_length_mm | body_mass_g |\n|:----------|---------------:|--------------:|------------------:|------------:|\n| Adelie    |        38.7914 |       18.3464 |           189.954 |     3700.66 |\n| Gentoo    |        47.5049 |       14.9821 |           217.187 |     5076.02 |\n| Chinstrap |        48.8338 |       18.4206 |           195.824 |     3733.09 |\n\n## 3.4 서식지별 펭귄 정보\n\n|     | island    | species   | sex    | count |\n|----:|:----------|:----------|:-------|------:|\n|   0 | Biscoe    | Adelie    | female |    22 |\n|   1 | Biscoe    | Adelie    | male   |    22 |\n|   2 | Biscoe    | Gentoo    | female |    58 |\n|   3 | Biscoe    | Gentoo    | male   |    61 |\n|   4 | Dream     | Adelie    | female |    27 |\n|   5 | Dream     | Adelie    | male   |    28 |\n|   6 | Dream     | Chinstrap | female |    34 |\n|   7 | Dream     | Chinstrap | male   |    34 |\n|   8 | Torgersen | Adelie    | female |    24 |\n|   9 | Torgersen | Adelie    | male   |    23 |\n\n1.  성비가 비교적 균형 잡혀 있음 (특히 Chinstrap 펭귄은 완전히 동일한 개체 수를 가짐).\n2.  Biscoe 섬에 Gentoo 펭귄이 가장 많음 (전체 119마리, 수컷이 약간 많음).\n3.  Dream 섬에는 Chinstrap 펭귄만 서식함.\n\n|     | island    | species   | count |\n|----:|:----------|:----------|------:|\n|   0 | Biscoe    | Adelie    |    44 |\n|   1 | Biscoe    | Gentoo    |   124 |\n|   2 | Dream     | Adelie    |    56 |\n|   3 | Dream     | Chinstrap |    68 |\n|   4 | Torgersen | Adelie    |    52 |\n\n1.  Biscoe 섬에 Gentoo 펭귄이 가장 많이 서식 (124마리).\n2.  Chinstrap 펭귄은 Dream 섬에만 분포 (총 68마리).\n3.  Adelie 펭귄은 모든 섬에 걸쳐 서식하지만, 개체 수가 비교적 고르게 분포됨.\n\n## 3.5 연도별 조사 표본 수\n\n|     | year | total_count |\n|:----|:----:|:-----------:|\n| 0   | 2007 |     110     |\n| 1   | 2008 |     114     |\n| 2   | 2009 |     120     |\n\n## 4. 종합 결론\n\n```         \n• 부리 길이: Chinstrap 펭귄 > Gentoo 펭귄 > Adelie 펭귄\n• 부리 깊이: Adelie ≈ Chinstrap > Gentoo\n• 날개 길이: Gentoo > Chinstrap > Adelie\n• 체중: Gentoo (가장 무거움) > Chinstrap ≈ Adelie\n• 개체 수: Biscoe 섬에 Gentoo 펭귄이 가장 많고, Dream 섬에는 Chinstrap 펭귄만 존재.\n```\n\n## 5. 개선사항\n\n-   데이터 해석 과정에서 오류가 있을 수 있음\n\n-   nan 값 및 이상치 처리 전후의 결과 비교를 추가로 고려할 필요성\n\n-   추후 분석 시 시각화 자료(그래프, 이미지) 등 보완 필요\n\n",
    "supporting": [
      "index_files"
    ],
    "filters": [],
    "includes": {}
  }
}